{
  "2025-01-31": {
    "du1_p": {
      "open": 1175528.96,
      "close_day": 1176098.8,
      "close_night": 1176165.19,
      "tests_day": 1,
      "tests_night": 0
    },
    "du1_d": {
      "open": 922292.06,
      "close_day": 923053.44,
      "close_night": 923222.69,
      "tests_day": 1,
      "tests_night": 0
    },
    "du2_p": {
      "open": 0,
      "close_day": 0,
      "close_night": 0,
      "tests_day": 0,
      "tests_night": 0
    },
    "du2_d": {
      "open": 0,
      "close_day": 0,
      "close_night": 0,
      "tests_day": 0,
      "tests_night": 0
    },
    "recon": {},
    "dip_ms_cm": 160.43,
    "dip_hsd_cm": 157.12,
    "_flags": [
      "du2_p_zero_sale_day",
      "du2_p_zero_sale_night",
      "du2_d_zero_sale_day",
      "du2_d_zero_sale_night"
    ],
    "_source": "honest"
  },
  "2025-01-30": {
    "du1_p": {
      "open": 1174956.02,
      "close_day": 1175439.07,
      "close_night": 1175528.96,
      "tests_day": 1,
      "tests_night": 0
    },
    "du1_d": {
      "open": 921411.59,
      "close_day": 922085.11,
      "close_night": 922292.06,
      "tests_day": 1,
      "tests_night": 0
    },
    "du2_p": {
      "open": 0,
      "close_day": 0,
      "close_night": 0,
      "tests_day": 0,
      "tests_night": 0
    },
    "du2_d": {
      "open": 0,
      "close_day": 0,
      "close_night": 0,
      "tests_day": 0,
      "tests_night": 0
    },
    "recon": {},
    "dip_ms_cm": 166.86,
    "dip_hsd_cm": 166.37,
    "_flags": [
      "du2_p_zero_sale_day",
      "du2_p_zero_sale_night",
      "du2_d_zero_sale_day",
      "du2_d_zero_sale_night"
    ],
    "_source": "honest"
  },
  "2025-01-29": {
    "du1_p": {
      "open": 1174412.16,
      "close_day": 1174877.16,
      "close_night": 1174956.02,
      "tests_day": 1,
      "tests_night": 0
    },
    "du1_d": {
      "open": 920856,
      "close_day": 921295.43,
      "close_night": 921411.59,
      "tests_day": 1,
      "tests_night": 0
    },
    "du2_p": {
      "open": 0,
      "close_day": 0,
      "close_night": 0,
      "tests_day": 0,
      "tests_night": 0
    },
    "du2_d": {
      "open": 0,
      "close_day": 0,
      "close_night": 0,
      "tests_day": 0,
      "tests_night": 0
    },
    "recon": {},
    "dip_ms_cm": 103.1,
    "dip_hsd_cm": 137.46,
    "_flags": [
      "du2_p_zero_sale_day",
      "du2_p_zero_sale_night",
      "du2_d_zero_sale_day",
      "du2_d_zero_sale_night"
    ],
    "_source": "honest"
  },
  "2025-01-28": {
    "du1_p": {
      "open": 1173896.3,
      "close_day": 1174376.53,
      "close_night": 1174412.16,
      "tests_day": 1,
      "tests_night": 0
    },
    "du1_d": {
      "open": 920145.15,
      "close_day": 920711.32,
      "close_night": 920856,
      "tests_day": 1,
      "tests_night": 0
    },
    "du2_p": {
      "open": 0,
      "close_day": 0,
      "close_night": 0,
      "tests_day": 0,
      "tests_night": 0
    },
    "du2_d": {
      "open": 0,
      "close_day": 0,
      "close_night": 0,
      "tests_day": 0,
      "tests_night": 0
    },
    "recon": {},
    "dip_ms_cm": 107.34,
    "dip_hsd_cm": 142.18,
    "_flags": [
      "du2_p_zero_sale_day",
      "du2_p_zero_sale_night",
      "du2_d_zero_sale_day",
      "du2_d_zero_sale_night"
    ],
    "_source": "honest"
  },
  "2025-01-27": {
    "du1_p": {
      "open": 1173335.9,
      "close_day": 1173810.56,
      "close_night": 1173896.3,
      "tests_day": 1,
      "tests_night": 0
    },
    "du1_d": {
      "open": 919273.96,
      "close_day": 920008.23,
      "close_night": 920145.15,
      "tests_day": 1,
      "tests_night": 0
    },
    "du2_p": {
      "open": 0,
      "close_day": 0,
      "close_night": 0,
      "tests_day": 0,
      "tests_night": 0
    },
    "du2_d": {
      "open": 0,
      "close_day": 0,
      "close_night": 0,
      "tests_day": 0,
      "tests_night": 0
    },
    "recon": {},
    "dip_ms_cm": 111.37,
    "dip_hsd_cm": 148.4,
    "_flags": [
      "du2_p_zero_sale_day",
      "du2_p_zero_sale_night",
      "du2_d_zero_sale_day",
      "du2_d_zero_sale_night"
    ],
    "_source": "honest"
  },
  "2025-01-26": {
    "du1_p": {
      "open": 1172779.67,
      "close_day": 1173272.31,
      "close_night": 1173335.9,
      "tests_day": 1,
      "tests_night": 0
    },
    "du1_d": {
      "open": 918424.15,
      "close_day": 919086.92,
      "close_night": 919273.96,
      "tests_day": 1,
      "tests_night": 0
    },
    "du2_p": {
      "open": 0,
      "close_day": 0,
      "close_night": 0,
      "tests_day": 0,
      "tests_night": 0
    },
    "du2_d": {
      "open": 0,
      "close_day": 0,
      "close_night": 0,
      "tests_day": 0,
      "tests_night": 0
    },
    "recon": {},
    "dip_ms_cm": 115.78,
    "dip_hsd_cm": 156.39,
    "_flags": [
      "du2_p_zero_sale_day",
      "du2_p_zero_sale_night",
      "du2_d_zero_sale_day",
      "du2_d_zero_sale_night"
    ],
    "_source": "honest"
  },
  "2025-01-25": {
    "du1_p": {
      "open": 1172262.2,
      "close_day": 1172779.67,
      "close_night": 1172779.67,
      "tests_day": 1,
      "tests_night": 0
    },
    "du1_d": {
      "open": 917602.61,
      "close_day": 918424.15,
      "close_night": 918424.15,
      "tests_day": 1,
      "tests_night": 0
    },
    "du2_p": {
      "open": 0,
      "close_day": 0,
      "close_night": 0,
      "tests_day": 0,
      "tests_night": 0
    },
    "du2_d": {
      "open": 0,
      "close_day": 0,
      "close_night": 0,
      "tests_day": 0,
      "tests_night": 0
    },
    "recon": {},
    "dip_ms_cm": 120.18,
    "dip_hsd_cm": 164.73,
    "_flags": [
      "du1_p_zero_sale_night",
      "du1_d_zero_sale_night",
      "du2_p_zero_sale_day",
      "du2_p_zero_sale_night",
      "du2_d_zero_sale_day",
      "du2_d_zero_sale_night"
    ],
    "_source": "honest"
  },
  "2025-01-24": {
    "du1_p": {
      "open": 1171720.83,
      "close_day": 1172171.95,
      "close_night": 1172262.2,
      "tests_day": 1,
      "tests_night": 0
    },
    "du1_d": {
      "open": 916741.93,
      "close_day": 917239.26,
      "close_night": 917602.61,
      "tests_day": 1,
      "tests_night": 0
    },
    "du2_p": {
      "open": 0,
      "close_day": 0,
      "close_night": 0,
      "tests_day": 0,
      "tests_night": 0
    },
    "du2_d": {
      "open": 0,
      "close_day": 0,
      "close_night": 0,
      "tests_day": 0,
      "tests_night": 0
    },
    "recon": {},
    "dip_ms_cm": 124.31,
    "dip_hsd_cm": 173.62,
    "_flags": [
      "du2_p_zero_sale_day",
      "du2_p_zero_sale_night",
      "du2_d_zero_sale_day",
      "du2_d_zero_sale_night"
    ],
    "_source": "honest"
  },
  "2025-01-23": {
    "du1_p": {
      "open": 1171157.72,
      "close_day": 1171677.84,
      "close_night": 1171720.83,
      "tests_day": 1,
      "tests_night": 0
    },
    "du1_d": {
      "open": 916032.48,
      "close_day": 916572.59,
      "close_night": 916741.93,
      "tests_day": 1,
      "tests_night": 0
    },
    "du2_p": {
      "open": 0,
      "close_day": 0,
      "close_night": 0,
      "tests_day": 0,
      "tests_night": 0
    },
    "du2_d": {
      "open": 0,
      "close_day": 0,
      "close_night": 0,
      "tests_day": 0,
      "tests_night": 0
    },
    "recon": {},
    "dip_ms_cm": 128.67,
    "dip_hsd_cm": 184.66,
    "_flags": [
      "du2_p_zero_sale_day",
      "du2_p_zero_sale_night",
      "du2_d_zero_sale_day",
      "du2_d_zero_sale_night"
    ],
    "_source": "honest"
  },
  "2025-01-22": {
    "du1_p": {
      "open": 1170649.25,
      "close_day": 1171085.87,
      "close_night": 1171157.72,
      "tests_day": 1,
      "tests_night": 0
    },
    "du1_d": {
      "open": 915217.66,
      "close_day": 915787.76,
      "close_night": 916032.48,
      "tests_day": 1,
      "tests_night": 0
    },
    "du2_p": {
      "open": 0,
      "close_day": 0,
      "close_night": 0,
      "tests_day": 0,
      "tests_night": 0
    },
    "du2_d": {
      "open": 0,
      "close_day": 0,
      "close_night": 0,
      "tests_day": 0,
      "tests_night": 0
    },
    "recon": {},
    "dip_ms_cm": 133.29,
    "dip_hsd_cm": 200.0,
    "_flags": [
      "du2_p_zero_sale_day",
      "du2_p_zero_sale_night",
      "du2_d_zero_sale_day",
      "du2_d_zero_sale_night"
    ],
    "_source": "honest"
  },
  "2025-01-21": {
    "du1_p": {
      "open": 1170122.12,
      "close_day": 1170541.25,
      "close_night": 1170649.25,
      "tests_day": 1,
      "tests_night": 0
    },
    "du1_d": {
      "open": 914487.2,
      "close_day": 914967.02,
      "close_night": 915217.66,
      "tests_day": 1,
      "tests_night": 0
    },
    "du2_p": {
      "open": 0,
      "close_day": 0,
      "close_night": 0,
      "tests_day": 0,
      "tests_night": 0
    },
    "du2_d": {
      "open": 0,
      "close_day": 0,
      "close_night": 0,
      "tests_day": 0,
      "tests_night": 0
    },
    "recon": {},
    "dip_ms_cm": 105.2,
    "dip_hsd_cm": 131.97,
    "_flags": [
      "du2_p_zero_sale_day",
      "du2_p_zero_sale_night",
      "du2_d_zero_sale_day",
      "du2_d_zero_sale_night"
    ],
    "_source": "honest"
  },
  "2025-01-20": {
    "du1_p": {
      "open": 1169402.86,
      "close_day": 1169965.38,
      "close_night": 1170122.12,
      "tests_day": 1,
      "tests_night": 0
    },
    "du1_d": {
      "open": 913665.5,
      "close_day": 914247.05,
      "close_night": 914487.2,
      "tests_day": 1,
      "tests_night": 0
    },
    "du2_p": {
      "open": 0,
      "close_day": 0,
      "close_night": 0,
      "tests_day": 0,
      "tests_night": 0
    },
    "du2_d": {
      "open": 0,
      "close_day": 0,
      "close_night": 0,
      "tests_day": 0,
      "tests_night": 0
    },
    "recon": {},
    "dip_ms_cm": 112.76,
    "dip_hsd_cm": 38.01,
    "_flags": [
      "du2_p_zero_sale_day",
      "du2_p_zero_sale_night",
      "du2_d_zero_sale_day",
      "du2_d_zero_sale_night"
    ],
    "_source": "honest"
  },
  "2025-01-19": {
    "du1_p": {
      "open": 1168854.15,
      "close_day": 1169346.3,
      "close_night": 1169402.86,
      "tests_day": 1,
      "tests_night": 0
    },
    "du1_d": {
      "open": 912985.46,
      "close_day": 913591.71,
      "close_night": 913665.5,
      "tests_day": 1,
      "tests_night": 0
    },
    "du2_p": {
      "open": 0,
      "close_day": 0,
      "close_night": 0,
      "tests_day": 0,
      "tests_night": 0
    },
    "du2_d": {
      "open": 0,
      "close_day": 0,
      "close_night": 0,
      "tests_day": 0,
      "tests_night": 0
    },
    "recon": {},
    "dip_ms_cm": 118.44,
    "dip_hsd_cm": 45.89,
    "_flags": [
      "du2_p_zero_sale_day",
      "du2_p_zero_sale_night",
      "du2_d_zero_sale_day",
      "du2_d_zero_sale_night"
    ],
    "_source": "honest"
  },
  "2025-01-18": {
    "du1_p": {
      "open": 1168379.9,
      "close_day": 1168758.87,
      "close_night": 1168854.15,
      "tests_day": 1,
      "tests_night": 0
    },
    "du1_d": {
      "open": 912327.49,
      "close_day": 912848.78,
      "close_night": 912985.46,
      "tests_day": 1,
      "tests_night": 0
    },
    "du2_p": {
      "open": 0,
      "close_day": 0,
      "close_night": 0,
      "tests_day": 0,
      "tests_night": 0
    },
    "du2_d": {
      "open": 0,
      "close_day": 0,
      "close_night": 0,
      "tests_day": 0,
      "tests_night": 0
    },
    "recon": {},
    "dip_ms_cm": 122.81,
    "dip_hsd_cm": 52.06,
    "_flags": [
      "du2_p_zero_sale_day",
      "du2_p_zero_sale_night",
      "du2_d_zero_sale_day",
      "du2_d_zero_sale_night"
    ],
    "_source": "honest"
  },
  "2025-01-17": {
    "du1_p": {
      "open": 1167804.36,
      "close_day": 1168272.52,
      "close_night": 1168379.9,
      "tests_day": 1,
      "tests_night": 0
    },
    "du1_d": {
      "open": 911458.07,
      "close_day": 912082.79,
      "close_night": 912327.49,
      "tests_day": 1,
      "tests_night": 0
    },
    "du2_p": {
      "open": 0,
      "close_day": 0,
      "close_night": 0,
      "tests_day": 0,
      "tests_night": 0
    },
    "du2_d": {
      "open": 0,
      "close_day": 0,
      "close_night": 0,
      "tests_day": 0,
      "tests_night": 0
    },
    "recon": {},
    "dip_ms_cm": 126.61,
    "dip_hsd_cm": 57.8,
    "_flags": [
      "du2_p_zero_sale_day",
      "du2_p_zero_sale_night",
      "du2_d_zero_sale_day",
      "du2_d_zero_sale_night"
    ],
    "_source": "honest"
  },
  "2025-01-16": {
    "du1_p": {
      "open": 1167253.32,
      "close_day": 1167750.89,
      "close_night": 1167804.36,
      "tests_day": 1,
      "tests_night": 0
    },
    "du1_d": {
      "open": 910584.08,
      "close_day": 911271.23,
      "close_night": 911458.07,
      "tests_day": 1,
      "tests_night": 0
    },
    "du2_p": {
      "open": 0,
      "close_day": 0,
      "close_night": 0,
      "tests_day": 0,
      "tests_night": 0
    },
    "du2_d": {
      "open": 0,
      "close_day": 0,
      "close_night": 0,
      "tests_day": 0,
      "tests_night": 0
    },
    "recon": {},
    "dip_ms_cm": 131.29,
    "dip_hsd_cm": 65.16,
    "_flags": [
      "du2_p_zero_sale_day",
      "du2_p_zero_sale_night",
      "du2_d_zero_sale_day",
      "du2_d_zero_sale_night"
    ],
    "_source": "honest"
  },
  "2025-01-15": {
    "du1_p": {
      "open": 1166802.12,
      "close_day": 1167203.45,
      "close_night": 1167253.32,
      "tests_day": 1,
      "tests_night": 0
    },
    "du1_d": {
      "open": 909806.39,
      "close_day": 910382.61,
      "close_night": 910584.08,
      "tests_day": 1,
      "tests_night": 0
    },
    "du2_p": {
      "open": 0,
      "close_day": 0,
      "close_night": 0,
      "tests_day": 0,
      "tests_night": 0
    },
    "du2_d": {
      "open": 0,
      "close_day": 0,
      "close_night": 0,
      "tests_day": 0,
      "tests_night": 0
    },
    "recon": {},
    "dip_ms_cm": 135.85,
    "dip_hsd_cm": 72.35,
    "_flags": [
      "du2_p_zero_sale_day",
      "du2_p_zero_sale_night",
      "du2_d_zero_sale_day",
      "du2_d_zero_sale_night"
    ],
    "_source": "honest"
  },
  "2025-01-14": {
    "du1_p": {
      "open": 1166287.62,
      "close_day": 1166736.11,
      "close_night": 1166802.12,
      "tests_day": 1,
      "tests_night": 0
    },
    "du1_d": {
      "open": 909242.85,
      "close_day": 909593.34,
      "close_night": 909806.39,
      "tests_day": 1,
      "tests_night": 0
    },
    "du2_p": {
      "open": 0,
      "close_day": 0,
      "close_night": 0,
      "tests_day": 0,
      "tests_night": 0
    },
    "du2_d": {
      "open": 0,
      "close_day": 0,
      "close_night": 0,
      "tests_day": 0,
      "tests_night": 0
    },
    "recon": {},
    "dip_ms_cm": 139.63,
    "dip_hsd_cm": 78.61,
    "_flags": [
      "du2_p_zero_sale_day",
      "du2_p_zero_sale_night",
      "du2_d_zero_sale_day",
      "du2_d_zero_sale_night"
    ],
    "_source": "honest"
  },
  "2025-01-13": {
    "du1_p": {
      "open": 1165864.04,
      "close_day": 1166232.89,
      "close_night": 1166287.62,
      "tests_day": 1,
      "tests_night": 0
    },
    "du1_d": {
      "open": 908504.29,
      "close_day": 909064.69,
      "close_night": 909242.85,
      "tests_day": 1,
      "tests_night": 0
    },
    "du2_p": {
      "open": 0,
      "close_day": 0,
      "close_night": 0,
      "tests_day": 0,
      "tests_night": 0
    },
    "du2_d": {
      "open": 0,
      "close_day": 0,
      "close_night": 0,
      "tests_day": 0,
      "tests_night": 0
    },
    "recon": {},
    "dip_ms_cm": 144.04,
    "dip_hsd_cm": 83.08,
    "_flags": [
      "du2_p_zero_sale_day",
      "du2_p_zero_sale_night",
      "du2_d_zero_sale_day",
      "du2_d_zero_sale_night"
    ],
    "_source": "honest"
  },
  "2025-01-12": {
    "du1_p": {
      "open": 1165497.01,
      "close_day": 1165822.04,
      "close_night": 1165864.04,
      "tests_day": 1,
      "tests_night": 0
    },
    "du1_d": {
      "open": 907663.46,
      "close_day": 908386.08,
      "close_night": 908504.29,
      "tests_day": 1,
      "tests_night": 0
    },
    "du2_p": {
      "open": 0,
      "close_day": 0,
      "close_night": 0,
      "tests_day": 0,
      "tests_night": 0
    },
    "du2_d": {
      "open": 0,
      "close_day": 0,
      "close_night": 0,
      "tests_day": 0,
      "tests_night": 0
    },
    "recon": {},
    "dip_ms_cm": 147.74,
    "dip_hsd_cm": 88.9,
    "_flags": [
      "du2_p_zero_sale_day",
      "du2_p_zero_sale_night",
      "du2_d_zero_sale_day",
      "du2_d_zero_sale_night"
    ],
    "_source": "honest"
  },
  "2025-01-11": {
    "du1_p": {
      "open": 1165209.87,
      "close_day": 1165452.52,
      "close_night": 1165497.01,
      "tests_day": 1,
      "tests_night": 0
    },
    "du1_d": {
      "open": 906934.89,
      "close_day": 907445.78,
      "close_night": 907663.46,
      "tests_day": 1,
      "tests_night": 0
    },
    "du2_p": {
      "open": 0,
      "close_day": 0,
      "close_night": 0,
      "tests_day": 0,
      "tests_night": 0
    },
    "du2_d": {
      "open": 0,
      "close_day": 0,
      "close_night": 0,
      "tests_day": 0,
      "tests_night": 0
    },
    "recon": {},
    "dip_ms_cm": 151.01,
    "dip_hsd_cm": 95.49,
    "_flags": [
      "du2_p_zero_sale_day",
      "du2_p_zero_sale_night",
      "du2_d_zero_sale_day",
      "du2_d_zero_sale_night"
    ],
    "_source": "honest"
  },
  "2025-01-10": {
    "du1_p": {
      "open": 1164667.88,
      "close_day": 1165173.27,
      "close_night": 1165209.87,
      "tests_day": 1,
      "tests_night": 0
    },
    "du1_d": {
      "open": 906030.49,
      "close_day": 906712.25,
      "close_night": 906934.89,
      "tests_day": 1,
      "tests_night": 0
    },
    "du2_p": {
      "open": 0,
      "close_day": 0,
      "close_night": 0,
      "tests_day": 0,
      "tests_night": 0
    },
    "du2_d": {
      "open": 0,
      "close_day": 0,
      "close_night": 0,
      "tests_day": 0,
      "tests_night": 0
    },
    "recon": {},
    "dip_ms_cm": 119.63,
    "dip_hsd_cm": 32.89,
    "_flags": [
      "du2_p_zero_sale_day",
      "du2_p_zero_sale_night",
      "du2_d_zero_sale_day",
      "du2_d_zero_sale_night"
    ],
    "_source": "honest"
  },
  "2025-01-09": {
    "du1_p": {
      "open": 1164092.19,
      "close_day": 1164600.92,
      "close_night": 1164667.88,
      "tests_day": 1,
      "tests_night": 0
    },
    "du1_d": {
      "open": 905297.13,
      "close_day": 905873.08,
      "close_night": 906030.49,
      "tests_day": 1,
      "tests_night": 0
    },
    "du2_p": {
      "open": 0,
      "close_day": 0,
      "close_night": 0,
      "tests_day": 0,
      "tests_night": 0
    },
    "du2_d": {
      "open": 0,
      "close_day": 0,
      "close_night": 0,
      "tests_day": 0,
      "tests_night": 0
    },
    "recon": {},
    "dip_ms_cm": 123.95,
    "dip_hsd_cm": 41.95,
    "_flags": [
      "du2_p_zero_sale_day",
      "du2_p_zero_sale_night",
      "du2_d_zero_sale_day",
      "du2_d_zero_sale_night"
    ],
    "_source": "honest"
  },
  "2025-01-08": {
    "du1_p": {
      "open": 1163572.39,
      "close_day": 1164036.64,
      "close_night": 1164092.19,
      "tests_day": 1,
      "tests_night": 0
    },
    "du1_d": {
      "open": 904445.4,
      "close_day": 905142.19,
      "close_night": 905297.13,
      "tests_day": 1,
      "tests_night": 0
    },
    "du2_p": {
      "open": 0,
      "close_day": 0,
      "close_night": 0,
      "tests_day": 0,
      "tests_night": 0
    },
    "du2_d": {
      "open": 0,
      "close_day": 0,
      "close_night": 0,
      "tests_day": 0,
      "tests_night": 0
    },
    "recon": {},
    "dip_ms_cm": 128.59,
    "dip_hsd_cm": 48.79,
    "_flags": [
      "du2_p_zero_sale_day",
      "du2_p_zero_sale_night",
      "du2_d_zero_sale_day",
      "du2_d_zero_sale_night"
    ],
    "_source": "honest"
  },
  "2025-01-07": {
    "du1_p": {
      "open": 1163157.29,
      "close_day": 1163515.67,
      "close_night": 1163572.39,
      "tests_day": 1,
      "tests_night": 0
    },
    "du1_d": {
      "open": 903814.61,
      "close_day": 904306.74,
      "close_night": 904445.4,
      "tests_day": 1,
      "tests_night": 0
    },
    "du2_p": {
      "open": 0,
      "close_day": 0,
      "close_night": 0,
      "tests_day": 0,
      "tests_night": 0
    },
    "du2_d": {
      "open": 0,
      "close_day": 0,
      "close_night": 0,
      "tests_day": 0,
      "tests_night": 0
    },
    "recon": {},
    "dip_ms_cm": 132.84,
    "dip_hsd_cm": 56.34,
    "_flags": [
      "du2_p_zero_sale_day",
      "du2_p_zero_sale_night",
      "du2_d_zero_sale_day",
      "du2_d_zero_sale_night"
    ],
    "_source": "honest"
  },
  "2025-01-06": {
    "du1_p": {
      "open": 1162611.75,
      "close_day": 1163119.36,
      "close_night": 1163157.29,
      "tests_day": 1,
      "tests_night": 0
    },
    "du1_d": {
      "open": 903105.13,
      "close_day": 903706.68,
      "close_night": 903814.61,
      "tests_day": 1,
      "tests_night": 0
    },
    "du2_p": {
      "open": 0,
      "close_day": 0,
      "close_night": 0,
      "tests_day": 0,
      "tests_night": 0
    },
    "du2_d": {
      "open": 0,
      "close_day": 0,
      "close_night": 0,
      "tests_day": 0,
      "tests_night": 0
    },
    "recon": {},
    "dip_ms_cm": 136.28,
    "dip_hsd_cm": 61.73,
    "_flags": [
      "du2_p_zero_sale_day",
      "du2_p_zero_sale_night",
      "du2_d_zero_sale_day",
      "du2_d_zero_sale_night"
    ],
    "_source": "honest"
  },
  "2025-01-05": {
    "du1_p": {
      "open": 1162004.12,
      "close_day": 1162483.91,
      "close_night": 1162611.75,
      "tests_day": 1,
      "tests_night": 0
    },
    "du1_d": {
      "open": 902502.9,
      "close_day": 903025.29,
      "close_night": 903105.13,
      "tests_day": 1,
      "tests_night": 0
    },
    "du2_p": {
      "open": 0,
      "close_day": 0,
      "close_night": 0,
      "tests_day": 0,
      "tests_night": 0
    },
    "du2_d": {
      "open": 0,
      "close_day": 0,
      "close_night": 0,
      "tests_day": 0,
      "tests_night": 0
    },
    "recon": {},
    "dip_ms_cm": 140.88,
    "dip_hsd_cm": 67.65,
    "_flags": [
      "du2_p_zero_sale_day",
      "du2_p_zero_sale_night",
      "du2_d_zero_sale_day",
      "du2_d_zero_sale_night"
    ],
    "_source": "honest"
  },
  "2025-01-04": {
    "du1_p": {
      "open": 1161500.57,
      "close_day": 1161950.49,
      "close_night": 1162004.12,
      "tests_day": 1,
      "tests_night": 0
    },
    "du1_d": {
      "open": 901923.07,
      "close_day": 902321.01,
      "close_night": 902502.9,
      "tests_day": 1,
      "tests_night": 0
    },
    "du2_p": {
      "open": 0,
      "close_day": 0,
      "close_night": 0,
      "tests_day": 0,
      "tests_night": 0
    },
    "du2_d": {
      "open": 0,
      "close_day": 0,
      "close_night": 0,
      "tests_day": 0,
      "tests_night": 0
    },
    "recon": {},
    "dip_ms_cm": 146.14,
    "dip_hsd_cm": 72.56,
    "_flags": [
      "du2_p_zero_sale_day",
      "du2_p_zero_sale_night",
      "du2_d_zero_sale_day",
      "du2_d_zero_sale_night"
    ],
    "_source": "honest"
  },
  "2025-01-03": {
    "du1_p": {
      "open": 1161044.28,
      "close_day": 1161423.09,
      "close_night": 1161500.57,
      "tests_day": 1,
      "tests_night": 0
    },
    "du1_d": {
      "open": 901365.57,
      "close_day": 901802.81,
      "close_night": 901923.07,
      "tests_day": 1,
      "tests_night": 0
    },
    "du2_p": {
      "open": 0,
      "close_day": 0,
      "close_night": 0,
      "tests_day": 0,
      "tests_night": 0
    },
    "du2_d": {
      "open": 0,
      "close_day": 0,
      "close_night": 0,
      "tests_day": 0,
      "tests_night": 0
    },
    "recon": {},
    "dip_ms_cm": 150.61,
    "dip_hsd_cm": 77.23,
    "_flags": [
      "du2_p_zero_sale_day",
      "du2_p_zero_sale_night",
      "du2_d_zero_sale_day",
      "du2_d_zero_sale_night"
    ],
    "_source": "honest"
  },
  "2025-01-02": {
    "du1_p": {
      "open": 1160483.13,
      "close_day": 1160991.94,
      "close_night": 1161044.28,
      "tests_day": 1,
      "tests_night": 0
    },
    "du1_d": {
      "open": 900603.44,
      "close_day": 901140.79,
      "close_night": 901365.57,
      "tests_day": 1,
      "tests_night": 0
    },
    "du2_p": {
      "open": 0,
      "close_day": 0,
      "close_night": 0,
      "tests_day": 0,
      "tests_night": 0
    },
    "du2_d": {
      "open": 0,
      "close_day": 0,
      "close_night": 0,
      "tests_day": 0,
      "tests_night": 0
    },
    "recon": {},
    "dip_ms_cm": 154.78,
    "dip_hsd_cm": 81.66,
    "_flags": [
      "du2_p_zero_sale_day",
      "du2_p_zero_sale_night",
      "du2_d_zero_sale_day",
      "du2_d_zero_sale_night"
    ],
    "_source": "honest"
  },
  "2025-01-01": {
    "du1_p": {
      "open": 1159979.4,
      "close_day": 1160429.29,
      "close_night": 1160483.13,
      "tests_day": 1,
      "tests_night": 0
    },
    "du1_d": {
      "open": 899916.65,
      "close_day": 900546.4,
      "close_night": 900603.44,
      "tests_day": 1,
      "tests_night": 0
    },
    "du2_p": {
      "open": 0,
      "close_day": 0,
      "close_night": 0,
      "tests_day": 0,
      "tests_night": 0
    },
    "du2_d": {
      "open": 0,
      "close_day": 0,
      "close_night": 0,
      "tests_day": 0,
      "tests_night": 0
    },
    "recon": {},
    "dip_ms_cm": 163.91,
    "dip_hsd_cm": 87.68,
    "_flags": [
      "du2_p_zero_sale_day",
      "du2_p_zero_sale_night",
      "du2_d_zero_sale_day",
      "du2_d_zero_sale_night"
    ],
    "_source": "honest"
  }
}